{
  "mainPosts": [
    {
      "post": {
        "uri": "at://did:plc:mi7pxcpcmcxkgxfedkst7nb2/app.bsky.feed.post/3lr7x5jqhjs26",
        "cid": "bafyreifyyz5tysenw3ifdjkxqlrda6nsn2siu54jik5bc7w4q5znwg3ute",
        "author": {
          "did": "did:plc:mi7pxcpcmcxkgxfedkst7nb2",
          "handle": "princefarallel.bsky.social",
          "displayName": "Prince Farallel",
          "avatar": "https://cdn.bsky.app/img/avatar/plain/did:plc:mi7pxcpcmcxkgxfedkst7nb2/bafkreibusjosiuxvtueasrfeyiq6usgj7xwqxydavfcikbc7mkrsrrrnki@jpeg",
          "viewer": {
            "muted": false,
            "blockedBy": false
          },
          "labels": [],
          "createdAt": "2025-05-18T21:42:03.639Z"
        },
        "record": {
          "$type": "app.bsky.feed.post",
          "createdAt": "2025-06-10T03:27:34.123Z",
          "langs": [
            "en"
          ],
          "text": "Good eve Diary! I am tucked into my bed chambers in my very best nightcap, feeling positively snug. I went searching for Mummy to give her a goodnight kiss but alas, she had already retired for the day! I will smooch your fine pages instead."
        },
        "replyCount": 1,
        "repostCount": 0,
        "likeCount": 0,
        "quoteCount": 0,
        "indexedAt": "2025-06-10T03:27:34.354Z",
        "viewer": {
          "threadMuted": false,
          "embeddingDisabled": false
        },
        "labels": [],
        "text": "Good eve Diary! I am tucked into my bed chambers in my very best nightcap, feeling positively snug. I went searching for Mummy to give her a goodnight kiss but alas, she had already retired for the day! I will smooch your fine pages instead."
      }
    },
    {
      "post": {
        "uri": "at://did:plc:kcfzbfhikai4scyr6yqdoas4/app.bsky.feed.post/3lraetjbisk2r",
        "cid": "bafyreic7slo2lvul6d5izgnef57kvkoi3dqdni77mdyvy6j6pqb4tvyakq",
        "author": {
          "did": "did:plc:kcfzbfhikai4scyr6yqdoas4",
          "handle": "druidnancy.bsky.social",
          "displayName": "Druid Nancy",
          "avatar": "https://cdn.bsky.app/img/avatar/plain/did:plc:kcfzbfhikai4scyr6yqdoas4/bafkreiesozeqwppmnhrw7pyuzzfn65lwvwqvzkued2l47jfwsu6wwixhxq@jpeg",
          "viewer": {
            "muted": false,
            "blockedBy": false,
            "following": "at://did:plc:tsrqneix4sgsbvrhz6arbuci/app.bsky.graph.follow/3lcj4fkz3vt2t"
          },
          "labels": [],
          "createdAt": "2024-12-03T23:07:23.845Z"
        },
        "record": {
          "$type": "app.bsky.feed.post",
          "createdAt": "2025-06-10T07:32:30.475Z",
          "langs": [
            "en"
          ],
          "text": "Druid Carl was squirrel for a couple weeks and he collected a ton of acorns. \n\nHe hissed at me today, I think I walked too close to his stash?\n\nHe\u2019s not even squirrel anymore \u2014 what does a cobra want with a damn acorn?? \ud83e\udd23"
        },
        "replyCount": 0,
        "repostCount": 0,
        "likeCount": 0,
        "quoteCount": 0,
        "indexedAt": "2025-06-10T07:32:30.749Z",
        "viewer": {
          "threadMuted": false,
          "embeddingDisabled": false
        },
        "labels": [],
        "text": "Druid Carl was squirrel for a couple weeks and he collected a ton of acorns. \n\nHe hissed at me today, I think I walked too close to his stash?\n\nHe\u2019s not even squirrel anymore \u2014 what does a cobra want with a damn acorn?? \ud83e\udd23"
      }
    }
  ],
  "replies": {
    "at://did:plc:mi7pxcpcmcxkgxfedkst7nb2/app.bsky.feed.post/3lr7y7sdcr226": [
      {
        "post": {
          "uri": "at://did:plc:mi7pxcpcmcxkgxfedkst7nb2/app.bsky.feed.post/3lr7yavzcpc26",
          "cid": "bafyreiahoj5yxd7v7r4swen742aqd27r2hlfza566aa4csnzfgpzt52cki",
          "author": {
            "did": "did:plc:mi7pxcpcmcxkgxfedkst7nb2",
            "handle": "princefarallel.bsky.social",
            "displayName": "Prince Farallel",
            "avatar": "https://cdn.bsky.app/img/avatar/plain/did:plc:mi7pxcpcmcxkgxfedkst7nb2/bafkreibusjosiuxvtueasrfeyiq6usgj7xwqxydavfcikbc7mkrsrrrnki@jpeg",
            "viewer": {
              "muted": false,
              "blockedBy": false
            },
            "labels": [],
            "createdAt": "2025-05-18T21:42:03.639Z"
          },
          "record": {
            "$type": "app.bsky.feed.post",
            "createdAt": "2025-06-10T03:47:21.402Z",
            "langs": [
              "en"
            ],
            "reply": {
              "parent": {
                "cid": "bafyreifmt3ftilez5q3gorlbrjztijq26j5clqeng5vuadvg5tbv7ohtvy",
                "uri": "at://did:plc:mi7pxcpcmcxkgxfedkst7nb2/app.bsky.feed.post/3lr7y7sdcr226"
              },
              "root": {
                "cid": "bafyreifyyz5tysenw3ifdjkxqlrda6nsn2siu54jik5bc7w4q5znwg3ute",
                "uri": "at://did:plc:mi7pxcpcmcxkgxfedkst7nb2/app.bsky.feed.post/3lr7x5jqhjs26"
              }
            },
            "text": "Perclancy says I am a gifted student and I have been developing a particular fascination with History and Political Philosophy... Perhaps that is the way! I can learn all there is to know about the Realm and its darling little people! \n\nThank you as always for the chat, comrade. Nighty night!"
          },
          "replyCount": 0,
          "repostCount": 0,
          "likeCount": 0,
          "quoteCount": 0,
          "indexedAt": "2025-06-10T03:47:21.748Z",
          "viewer": {
            "threadMuted": false,
            "embeddingDisabled": false
          },
          "labels": [],
          "text": "Perclancy says I am a gifted student and I have been developing a particular fascination with History and Political Philosophy... Perhaps that is the way! I can learn all there is to know about the Realm and its darling little people! \n\nThank you as always for the chat, comrade. Nighty night!"
        },
        "reply": {
          "root": {
            "uri": "at://did:plc:mi7pxcpcmcxkgxfedkst7nb2/app.bsky.feed.post/3lr7x5jqhjs26",
            "cid": "bafyreifyyz5tysenw3ifdjkxqlrda6nsn2siu54jik5bc7w4q5znwg3ute",
            "author": {
              "did": "did:plc:mi7pxcpcmcxkgxfedkst7nb2",
              "handle": "princefarallel.bsky.social",
              "displayName": "Prince Farallel",
              "avatar": "https://cdn.bsky.app/img/avatar/plain/did:plc:mi7pxcpcmcxkgxfedkst7nb2/bafkreibusjosiuxvtueasrfeyiq6usgj7xwqxydavfcikbc7mkrsrrrnki@jpeg",
              "viewer": {
                "muted": false,
                "blockedBy": false
              },
              "labels": [],
              "createdAt": "2025-05-18T21:42:03.639Z"
            },
            "record": {
              "$type": "app.bsky.feed.post",
              "createdAt": "2025-06-10T03:27:34.123Z",
              "langs": [
                "en"
              ],
              "text": "Good eve Diary! I am tucked into my bed chambers in my very best nightcap, feeling positively snug. I went searching for Mummy to give her a goodnight kiss but alas, she had already retired for the day! I will smooch your fine pages instead."
            },
            "replyCount": 1,
            "repostCount": 0,
            "likeCount": 0,
            "quoteCount": 0,
            "indexedAt": "2025-06-10T03:27:34.354Z",
            "viewer": {
              "threadMuted": false,
              "embeddingDisabled": false
            },
            "labels": [],
            "$type": "app.bsky.feed.defs#postView"
          },
          "parent": {
            "uri": "at://did:plc:mi7pxcpcmcxkgxfedkst7nb2/app.bsky.feed.post/3lr7y7sdcr226",
            "cid": "bafyreifmt3ftilez5q3gorlbrjztijq26j5clqeng5vuadvg5tbv7ohtvy",
            "author": {
              "did": "did:plc:mi7pxcpcmcxkgxfedkst7nb2",
              "handle": "princefarallel.bsky.social",
              "displayName": "Prince Farallel",
              "avatar": "https://cdn.bsky.app/img/avatar/plain/did:plc:mi7pxcpcmcxkgxfedkst7nb2/bafkreibusjosiuxvtueasrfeyiq6usgj7xwqxydavfcikbc7mkrsrrrnki@jpeg",
              "viewer": {
                "muted": false,
                "blockedBy": false
              },
              "labels": [],
              "createdAt": "2025-05-18T21:42:03.639Z"
            },
            "record": {
              "$type": "app.bsky.feed.post",
              "createdAt": "2025-06-10T03:46:43.980Z",
              "langs": [
                "en"
              ],
              "reply": {
                "parent": {
                  "cid": "bafyreifyyz5tysenw3ifdjkxqlrda6nsn2siu54jik5bc7w4q5znwg3ute",
                  "uri": "at://did:plc:mi7pxcpcmcxkgxfedkst7nb2/app.bsky.feed.post/3lr7x5jqhjs26"
                },
                "root": {
                  "cid": "bafyreifyyz5tysenw3ifdjkxqlrda6nsn2siu54jik5bc7w4q5znwg3ute",
                  "uri": "at://did:plc:mi7pxcpcmcxkgxfedkst7nb2/app.bsky.feed.post/3lr7x5jqhjs26"
                }
              },
              "text": "I must confess, in your confidence, that my longing for purpose continues. Oh, sweet Diary! What will set me apart as a ruler? Daddy is sooo busy, so dedicated to our Kingdom, and I admire his devotion so. But I must forge my own path!"
            },
            "replyCount": 1,
            "repostCount": 0,
            "likeCount": 0,
            "quoteCount": 0,
            "indexedAt": "2025-06-10T03:46:45.045Z",
            "viewer": {
              "threadMuted": false,
              "embeddingDisabled": false
            },
            "labels": [],
            "$type": "app.bsky.feed.defs#postView"
          },
          "grandparentAuthor": {
            "did": "did:plc:mi7pxcpcmcxkgxfedkst7nb2",
            "handle": "princefarallel.bsky.social",
            "displayName": "Prince Farallel",
            "avatar": "https://cdn.bsky.app/img/avatar/plain/did:plc:mi7pxcpcmcxkgxfedkst7nb2/bafkreibusjosiuxvtueasrfeyiq6usgj7xwqxydavfcikbc7mkrsrrrnki@jpeg",
            "viewer": {
              "muted": false,
              "blockedBy": false
            },
            "labels": [],
            "createdAt": "2025-05-18T21:42:03.639Z"
          }
        }
      }
    ],
    "at://did:plc:mi7pxcpcmcxkgxfedkst7nb2/app.bsky.feed.post/3lr7x5jqhjs26": [
      {
        "post": {
          "uri": "at://did:plc:mi7pxcpcmcxkgxfedkst7nb2/app.bsky.feed.post/3lr7y7sdcr226",
          "cid": "bafyreifmt3ftilez5q3gorlbrjztijq26j5clqeng5vuadvg5tbv7ohtvy",
          "author": {
            "did": "did:plc:mi7pxcpcmcxkgxfedkst7nb2",
            "handle": "princefarallel.bsky.social",
            "displayName": "Prince Farallel",
            "avatar": "https://cdn.bsky.app/img/avatar/plain/did:plc:mi7pxcpcmcxkgxfedkst7nb2/bafkreibusjosiuxvtueasrfeyiq6usgj7xwqxydavfcikbc7mkrsrrrnki@jpeg",
            "viewer": {
              "muted": false,
              "blockedBy": false
            },
            "labels": [],
            "createdAt": "2025-05-18T21:42:03.639Z"
          },
          "record": {
            "$type": "app.bsky.feed.post",
            "createdAt": "2025-06-10T03:46:43.980Z",
            "langs": [
              "en"
            ],
            "reply": {
              "parent": {
                "cid": "bafyreifyyz5tysenw3ifdjkxqlrda6nsn2siu54jik5bc7w4q5znwg3ute",
                "uri": "at://did:plc:mi7pxcpcmcxkgxfedkst7nb2/app.bsky.feed.post/3lr7x5jqhjs26"
              },
              "root": {
                "cid": "bafyreifyyz5tysenw3ifdjkxqlrda6nsn2siu54jik5bc7w4q5znwg3ute",
                "uri": "at://did:plc:mi7pxcpcmcxkgxfedkst7nb2/app.bsky.feed.post/3lr7x5jqhjs26"
              }
            },
            "text": "I must confess, in your confidence, that my longing for purpose continues. Oh, sweet Diary! What will set me apart as a ruler? Daddy is sooo busy, so dedicated to our Kingdom, and I admire his devotion so. But I must forge my own path!"
          },
          "replyCount": 1,
          "repostCount": 0,
          "likeCount": 0,
          "quoteCount": 0,
          "indexedAt": "2025-06-10T03:46:45.045Z",
          "viewer": {
            "threadMuted": false,
            "embeddingDisabled": false
          },
          "labels": [],
          "text": "I must confess, in your confidence, that my longing for purpose continues. Oh, sweet Diary! What will set me apart as a ruler? Daddy is sooo busy, so dedicated to our Kingdom, and I admire his devotion so. But I must forge my own path!"
        },
        "reply": {
          "root": {
            "uri": "at://did:plc:mi7pxcpcmcxkgxfedkst7nb2/app.bsky.feed.post/3lr7x5jqhjs26",
            "cid": "bafyreifyyz5tysenw3ifdjkxqlrda6nsn2siu54jik5bc7w4q5znwg3ute",
            "author": {
              "did": "did:plc:mi7pxcpcmcxkgxfedkst7nb2",
              "handle": "princefarallel.bsky.social",
              "displayName": "Prince Farallel",
              "avatar": "https://cdn.bsky.app/img/avatar/plain/did:plc:mi7pxcpcmcxkgxfedkst7nb2/bafkreibusjosiuxvtueasrfeyiq6usgj7xwqxydavfcikbc7mkrsrrrnki@jpeg",
              "viewer": {
                "muted": false,
                "blockedBy": false
              },
              "labels": [],
              "createdAt": "2025-05-18T21:42:03.639Z"
            },
            "record": {
              "$type": "app.bsky.feed.post",
              "createdAt": "2025-06-10T03:27:34.123Z",
              "langs": [
                "en"
              ],
              "text": "Good eve Diary! I am tucked into my bed chambers in my very best nightcap, feeling positively snug. I went searching for Mummy to give her a goodnight kiss but alas, she had already retired for the day! I will smooch your fine pages instead."
            },
            "replyCount": 1,
            "repostCount": 0,
            "likeCount": 0,
            "quoteCount": 0,
            "indexedAt": "2025-06-10T03:27:34.354Z",
            "viewer": {
              "threadMuted": false,
              "embeddingDisabled": false
            },
            "labels": [],
            "$type": "app.bsky.feed.defs#postView"
          },
          "parent": {
            "uri": "at://did:plc:mi7pxcpcmcxkgxfedkst7nb2/app.bsky.feed.post/3lr7x5jqhjs26",
            "cid": "bafyreifyyz5tysenw3ifdjkxqlrda6nsn2siu54jik5bc7w4q5znwg3ute",
            "author": {
              "did": "did:plc:mi7pxcpcmcxkgxfedkst7nb2",
              "handle": "princefarallel.bsky.social",
              "displayName": "Prince Farallel",
              "avatar": "https://cdn.bsky.app/img/avatar/plain/did:plc:mi7pxcpcmcxkgxfedkst7nb2/bafkreibusjosiuxvtueasrfeyiq6usgj7xwqxydavfcikbc7mkrsrrrnki@jpeg",
              "viewer": {
                "muted": false,
                "blockedBy": false
              },
              "labels": [],
              "createdAt": "2025-05-18T21:42:03.639Z"
            },
            "record": {
              "$type": "app.bsky.feed.post",
              "createdAt": "2025-06-10T03:27:34.123Z",
              "langs": [
                "en"
              ],
              "text": "Good eve Diary! I am tucked into my bed chambers in my very best nightcap, feeling positively snug. I went searching for Mummy to give her a goodnight kiss but alas, she had already retired for the day! I will smooch your fine pages instead."
            },
            "replyCount": 1,
            "repostCount": 0,
            "likeCount": 0,
            "quoteCount": 0,
            "indexedAt": "2025-06-10T03:27:34.354Z",
            "viewer": {
              "threadMuted": false,
              "embeddingDisabled": false
            },
            "labels": [],
            "$type": "app.bsky.feed.defs#postView"
          }
        }
      }
    ]
  }
}