{
  "mainPosts": [
    {
      "post": {
        "uri": "at://did:plc:kcfzbfhikai4scyr6yqdoas4/app.bsky.feed.post/3m323wfiwxk2e",
        "cid": "bafyreig7fazwfpj3afyxbglhfi3lirol4x22wj2opi7oauuoi4y4iz7q34",
        "author": {
          "did": "did:plc:kcfzbfhikai4scyr6yqdoas4",
          "handle": "druidnancy.bsky.social",
          "displayName": "Druid Nancy",
          "avatar": "https://cdn.bsky.app/img/avatar/plain/did:plc:kcfzbfhikai4scyr6yqdoas4/bafkreiesozeqwppmnhrw7pyuzzfn65lwvwqvzkued2l47jfwsu6wwixhxq@jpeg",
          "associated": {
            "activitySubscription": {
              "allowSubscriptions": "followers"
            }
          },
          "viewer": {
            "muted": false,
            "blockedBy": false,
            "following": "at://did:plc:tsrqneix4sgsbvrhz6arbuci/app.bsky.graph.follow/3lcj4fkz3vt2t"
          },
          "labels": [],
          "createdAt": "2024-12-03T23:07:23.845Z"
        },
        "record": {
          "$type": "app.bsky.feed.post",
          "createdAt": "2025-10-13T01:49:01.359Z",
          "langs": [
            "en"
          ],
          "text": "\ud83c\udf2b\ufe0f\ud83c\udf2b\ufe0f\ud83c\udf2b\ufe0f\ud83c\udf2b\ufe0f\ud83c\udf2b\ufe0f\ud83c\udf2b\ufe0f\ud83c\udf2b\ufe0f\ud83c\udf2b\ufe0f\ud83c\udf2b\ufe0f\ud83c\udf2b\ufe0f\ud83c\udf2b\ufe0f\ud83c\udf2b\ufe0f\ud83c\udf2b\ufe0f\ud83c\udf2b\ufe0f\ud83c\udf2b\ufe0f\ud83c\udf2b\ufe0f\ud83c\udf2b\ufe0f\ud83c\udf2b\ufe0f\ud83c\udf2b\ufe0f\ud83c\udf2b\ufe0f\ud83c\udf2b\ufe0f\ud83c\udf2b\ufe0f\ud83c\udf2b\ufe0f\ud83c\udf2b\ufe0f\ud83c\udf2b\ufe0f\ud83c\udf2b\ufe0f\ud83c\udf2b\ufe0f\ud83c\udf2b\ufe0f\ud83c\udf2b\ufe0f\ud83c\udf2b\ufe0f\ud83c\udf2b\ufe0f\ud83c\udf2b\ufe0f\ud83c\udf2b\ufe0f\ud83c\udf2b\ufe0f\ud83c\udf2b\ufe0f\ud83c\udf2b\ufe0f\ud83c\udf2b\ufe0f\ud83c\udf2b\ufe0f\ud83c\udf2b\ufe0f\ud83c\udf2b\ufe0f\ud83c\udf2b\ufe0f\ud83c\udf2b\ufe0f\ud83c\udf2b\ufe0f\ud83c\udf2b\ufe0f\ud83c\udf2b\ufe0f\ud83c\udf2b\ufe0f\ud83c\udf2b\ufe0f\ud83c\udf2b\ufe0f\ud83c\udf2b\ufe0f\ud83c\udf2b\ufe0f\ud83c\udf2b\ufe0f\ud83c\udf2b\ufe0f\ud83c\udf2b\ufe0f\ud83c\udf2b\ufe0f\ud83c\udf2b\ufe0f\ud83c\udf2b\ufe0f\ud83c\udf2b\ufe0f\ud83c\udf2b\ufe0f\ud83c\udf2b\ufe0f\ud83c\udf2b\ufe0f\ud83c\udf2b\ufe0f\ud83c\udf2b\ufe0f\ud83c\udf2b\ufe0f\ud83c\udf2b\ufe0f\ud83c\udf2b\ufe0f\ud83c\udf2b\ufe0f\ud83c\udf2b\ufe0f\ud83c\udf2b\ufe0f\ud83c\udf2b\ufe0f\ud83c\udf2b\ufe0f\ud83c\udf2b\ufe0f\ud83c\udf2b\ufe0f\ud83c\udf2b\ufe0f\ud83c\udf2b\ufe0f\ud83c\udf2b\ufe0f\ud83c\udf2b\ufe0f\ud83c\udf2b\ufe0f\ud83c\udf2b\ufe0f\ud83c\udf2b\ufe0f\ud83c\udf2b\ufe0f\ud83c\udf2b\ufe0f\ud83c\udf2b\ufe0f\ud83c\udf2b\ufe0f\ud83c\udf2b\ufe0f\ud83c\udf2b\ufe0f\ud83c\udf2b\ufe0f\ud83c\udf2b\ufe0f\ud83c\udf2b\ufe0f\ud83c\udf2b\ufe0f\ud83c\udf2b\ufe0f\ud83c\udf2b\ufe0f\ud83c\udf2b\ufe0f\ud83c\udf2b\ufe0f\ud83c\udf2b\ufe0f\ud83c\udf2b\ufe0f\ud83c\udf2b\ufe0f\ud83c\udf2b\ufe0f\ud83c\udf2b\ufe0f\ud83c\udf2b\ufe0f\ud83c\udf2b\ufe0f\ud83c\udf2b\ufe0f\ud83c\udf2b\ufe0f\ud83c\udf2b\ufe0f\ud83c\udf2b\ufe0f\ud83c\udf2b\ufe0f\ud83c\udf2b\ufe0f\ud83c\udf2b\ufe0f\ud83c\udf2b\ufe0f\ud83c\udf2b\ufe0f\ud83c\udf2b\ufe0f\ud83c\udf2b\ufe0f\ud83c\udf2b\ufe0f\ud83c\udf2b\ufe0f\ud83c\udf2b\ufe0f\ud83c\udf2b\ufe0f\ud83c\udf2b\ufe0f\ud83c\udf2b\ufe0f\ud83c\udf2b\ufe0f\ud83c\udf2b\ufe0f\ud83c\udf2b\ufe0f\ud83c\udf2b\ufe0f\ud83c\udf2b\ufe0f\ud83c\udf2b\ufe0f\ud83c\udf2b\ufe0f\ud83c\udf2b\ufe0f\ud83c\udf2b\ufe0f\ud83c\udf2b\ufe0f\ud83c\udf2b\ufe0f\ud83c\udf2b\ufe0f\ud83c\udf2b\ufe0f\ud83c\udf2b\ufe0f\ud83c\udf2b\ufe0f\ud83c\udf2b\ufe0f\ud83c\udf2b\ufe0f\ud83c\udf2b\ufe0f\ud83c\udf2b\ufe0f\ud83c\udf2b\ufe0f\ud83c\udf2b\ufe0f\ud83c\udf2b\ufe0f\ud83c\udf2b\ufe0f\ud83c\udf2b\ufe0f\ud83c\udf2b\ufe0f\ud83c\udf2b\ufe0f\ud83c\udf2b\ufe0f\ud83c\udf2b\ufe0f\ud83c\udf2b\ufe0f\ud83c\udf2b\ufe0f\ud83c\udf2b\ufe0f\ud83c\udf2b\ufe0f\ud83c\udf2b\ufe0f\ud83c\udf2b\ufe0f\ud83c\udf2b\ufe0f\ud83c\udf2b\ufe0f\ud83c\udf2b\ufe0f\ud83c\udf2b\ufe0f\ud83c\udf2b\ufe0f\ud83c\udf2b\ufe0f\ud83c\udf2b\ufe0f\ud83c\udf2b\ufe0f\ud83c\udf2b\ufe0f\ud83c\udf2b\ufe0f\ud83c\udf2b\ufe0f\ud83c\udf2b\ufe0f\ud83c\udf2b\ufe0f\ud83c\udf2b\ufe0f\ud83c\udf2b\ufe0f\ud83c\udf2b\ufe0f\ud83c\udf2b\ufe0f\ud83c\udf2b\ufe0f\ud83c\udf2b\ufe0f\ud83c\udf2b\ufe0f\ud83c\udf2b\ufe0f\ud83c\udf2b\ufe0f\ud83c\udf2b\ufe0f\ud83c\udf2b\ufe0f\ud83c\udf2b\ufe0f\ud83c\udf2b\ufe0f\ud83c\udf2b\ufe0f\ud83c\udf2b\ufe0f\ud83c\udf2b\ufe0f\ud83c\udf2b\ufe0f\ud83c\udf2b\ufe0f\ud83c\udf2b\ufe0f\ud83c\udf2b\ufe0f\ud83c\udf2b\ufe0f\ud83c\udf2b\ufe0f\ud83c\udf2b\ufe0f\ud83c\udf2b\ufe0f\ud83c\udf2b\ufe0f\ud83c\udf2b\ufe0f\ud83c\udf2b\ufe0f\ud83c\udf2b\ufe0f\ud83c\udf2b\ufe0f\ud83c\udf2b\ufe0f\ud83c\udf2b\ufe0f\ud83c\udf2b\ufe0f\ud83c\udf2b\ufe0f\ud83c\udf2b\ufe0f\ud83c\udf2b\ufe0f\ud83c\udf2b\ufe0f\ud83c\udf2b\ufe0f\ud83c\udf2b\ufe0f\ud83c\udf2b\ufe0f\ud83c\udf2b\ufe0f\ud83c\udf2b\ufe0f\ud83c\udf2b\ufe0f\ud83c\udf2b\ufe0f\ud83c\udf2b\ufe0f\ud83c\udf2b\ufe0f\ud83c\udf2b\ufe0f\ud83c\udf2b\ufe0f\ud83c\udf2b\ufe0f\ud83c\udf2b\ufe0f\ud83c\udf2b\ufe0f\ud83c\udf2b\ufe0f\ud83c\udf2b\ufe0f\ud83c\udf2b\ufe0f\ud83c\udf2b\ufe0f\ud83c\udf2b\ufe0f\ud83c\udf2b\ufe0f\ud83c\udf2b\ufe0f\ud83c\udf2b\ufe0f\ud83c\udf2b\ufe0f\ud83c\udf2b\ufe0f\ud83c\udf2b\ufe0f\ud83c\udf2b\ufe0f\ud83c\udf2b\ufe0f\ud83c\udf2b\ufe0f\ud83c\udf2b\ufe0f\ud83c\udf2b\ufe0f\ud83c\udf2b\ufe0f\ud83c\udf2b\ufe0f\ud83c\udf2b\ufe0f\ud83c\udf2b\ufe0f\ud83c\udf2b\ufe0f\ud83c\udf2b\ufe0f\ud83c\udf2b\ufe0f\ud83c\udf2b\ufe0f\ud83c\udf2b\ufe0f\ud83c\udf2b\ufe0f\ud83c\udf2b\ufe0f\ud83c\udf2b\ufe0f\ud83c\udf2b\ufe0f\ud83c\udf2b\ufe0f\ud83c\udf2b\ufe0f\ud83c\udf2b\ufe0f\ud83c\udf2b\ufe0f\ud83c\udf2b\ufe0f\ud83c\udf2b\ufe0f\ud83c\udf2b\ufe0f\ud83c\udf2b\ufe0f\ud83c\udf2b\ufe0f\ud83c\udf2b\ufe0f\ud83c\udf2b\ufe0f\ud83c\udf2b\ufe0f\ud83c\udf2b\ufe0f\ud83c\udf2b\ufe0f\ud83c\udf2b\ufe0f\ud83c\udf2b\ufe0f\ud83c\udf2b\ufe0f\ud83c\udf2b\ufe0f\ud83c\udf2b\ufe0f\ud83c\udf2b\ufe0f\ud83c\udf2b\ufe0f\ud83c\udf2b\ufe0f\ud83c\udf2b\ufe0f\ud83c\udf2b\ufe0f\ud83c\udf2b\ufe0f\ud83c\udf2b\ufe0f\ud83c\udf2b\ufe0f\ud83c\udf2b\ufe0f\ud83c\udf2b\ufe0f\ud83c\udf2b\ufe0f\ud83c\udf2b\ufe0f\ud83c\udf2b\ufe0f\ud83c\udf2b\ufe0f\ud83c\udf2b\ufe0f\ud83c\udf2b\ufe0f\ud83c\udf2b\ufe0f\ud83c\udf2b\ufe0f"
        },
        "bookmarkCount": 0,
        "replyCount": 0,
        "repostCount": 0,
        "likeCount": 1,
        "quoteCount": 0,
        "indexedAt": "2025-10-13T01:49:02.478Z",
        "viewer": {
          "bookmarked": false,
          "threadMuted": false,
          "embeddingDisabled": false
        },
        "labels": [],
        "text": "\ud83c\udf2b\ufe0f\ud83c\udf2b\ufe0f\ud83c\udf2b\ufe0f\ud83c\udf2b\ufe0f\ud83c\udf2b\ufe0f\ud83c\udf2b\ufe0f\ud83c\udf2b\ufe0f\ud83c\udf2b\ufe0f\ud83c\udf2b\ufe0f\ud83c\udf2b\ufe0f\ud83c\udf2b\ufe0f\ud83c\udf2b\ufe0f\ud83c\udf2b\ufe0f\ud83c\udf2b\ufe0f\ud83c\udf2b\ufe0f\ud83c\udf2b\ufe0f\ud83c\udf2b\ufe0f\ud83c\udf2b\ufe0f\ud83c\udf2b\ufe0f\ud83c\udf2b\ufe0f\ud83c\udf2b\ufe0f\ud83c\udf2b\ufe0f\ud83c\udf2b\ufe0f\ud83c\udf2b\ufe0f\ud83c\udf2b\ufe0f\ud83c\udf2b\ufe0f\ud83c\udf2b\ufe0f\ud83c\udf2b\ufe0f\ud83c\udf2b\ufe0f\ud83c\udf2b\ufe0f\ud83c\udf2b\ufe0f\ud83c\udf2b\ufe0f\ud83c\udf2b\ufe0f\ud83c\udf2b\ufe0f\ud83c\udf2b\ufe0f\ud83c\udf2b\ufe0f\ud83c\udf2b\ufe0f\ud83c\udf2b\ufe0f\ud83c\udf2b\ufe0f\ud83c\udf2b\ufe0f\ud83c\udf2b\ufe0f\ud83c\udf2b\ufe0f\ud83c\udf2b\ufe0f\ud83c\udf2b\ufe0f\ud83c\udf2b\ufe0f\ud83c\udf2b\ufe0f\ud83c\udf2b\ufe0f\ud83c\udf2b\ufe0f\ud83c\udf2b\ufe0f\ud83c\udf2b\ufe0f\ud83c\udf2b\ufe0f\ud83c\udf2b\ufe0f\ud83c\udf2b\ufe0f\ud83c\udf2b\ufe0f\ud83c\udf2b\ufe0f\ud83c\udf2b\ufe0f\ud83c\udf2b\ufe0f\ud83c\udf2b\ufe0f\ud83c\udf2b\ufe0f\ud83c\udf2b\ufe0f\ud83c\udf2b\ufe0f\ud83c\udf2b\ufe0f\ud83c\udf2b\ufe0f\ud83c\udf2b\ufe0f\ud83c\udf2b\ufe0f\ud83c\udf2b\ufe0f\ud83c\udf2b\ufe0f\ud83c\udf2b\ufe0f\ud83c\udf2b\ufe0f\ud83c\udf2b\ufe0f\ud83c\udf2b\ufe0f\ud83c\udf2b\ufe0f\ud83c\udf2b\ufe0f\ud83c\udf2b\ufe0f\ud83c\udf2b\ufe0f\ud83c\udf2b\ufe0f\ud83c\udf2b\ufe0f\ud83c\udf2b\ufe0f\ud83c\udf2b\ufe0f\ud83c\udf2b\ufe0f\ud83c\udf2b\ufe0f\ud83c\udf2b\ufe0f\ud83c\udf2b\ufe0f\ud83c\udf2b\ufe0f\ud83c\udf2b\ufe0f\ud83c\udf2b\ufe0f\ud83c\udf2b\ufe0f\ud83c\udf2b\ufe0f\ud83c\udf2b\ufe0f\ud83c\udf2b\ufe0f\ud83c\udf2b\ufe0f\ud83c\udf2b\ufe0f\ud83c\udf2b\ufe0f\ud83c\udf2b\ufe0f\ud83c\udf2b\ufe0f\ud83c\udf2b\ufe0f\ud83c\udf2b\ufe0f\ud83c\udf2b\ufe0f\ud83c\udf2b\ufe0f\ud83c\udf2b\ufe0f\ud83c\udf2b\ufe0f\ud83c\udf2b\ufe0f\ud83c\udf2b\ufe0f\ud83c\udf2b\ufe0f\ud83c\udf2b\ufe0f\ud83c\udf2b\ufe0f\ud83c\udf2b\ufe0f\ud83c\udf2b\ufe0f\ud83c\udf2b\ufe0f\ud83c\udf2b\ufe0f\ud83c\udf2b\ufe0f\ud83c\udf2b\ufe0f\ud83c\udf2b\ufe0f\ud83c\udf2b\ufe0f\ud83c\udf2b\ufe0f\ud83c\udf2b\ufe0f\ud83c\udf2b\ufe0f\ud83c\udf2b\ufe0f\ud83c\udf2b\ufe0f\ud83c\udf2b\ufe0f\ud83c\udf2b\ufe0f\ud83c\udf2b\ufe0f\ud83c\udf2b\ufe0f\ud83c\udf2b\ufe0f\ud83c\udf2b\ufe0f\ud83c\udf2b\ufe0f\ud83c\udf2b\ufe0f\ud83c\udf2b\ufe0f\ud83c\udf2b\ufe0f\ud83c\udf2b\ufe0f\ud83c\udf2b\ufe0f\ud83c\udf2b\ufe0f\ud83c\udf2b\ufe0f\ud83c\udf2b\ufe0f\ud83c\udf2b\ufe0f\ud83c\udf2b\ufe0f\ud83c\udf2b\ufe0f\ud83c\udf2b\ufe0f\ud83c\udf2b\ufe0f\ud83c\udf2b\ufe0f\ud83c\udf2b\ufe0f\ud83c\udf2b\ufe0f\ud83c\udf2b\ufe0f\ud83c\udf2b\ufe0f\ud83c\udf2b\ufe0f\ud83c\udf2b\ufe0f\ud83c\udf2b\ufe0f\ud83c\udf2b\ufe0f\ud83c\udf2b\ufe0f\ud83c\udf2b\ufe0f\ud83c\udf2b\ufe0f\ud83c\udf2b\ufe0f\ud83c\udf2b\ufe0f\ud83c\udf2b\ufe0f\ud83c\udf2b\ufe0f\ud83c\udf2b\ufe0f\ud83c\udf2b\ufe0f\ud83c\udf2b\ufe0f\ud83c\udf2b\ufe0f\ud83c\udf2b\ufe0f\ud83c\udf2b\ufe0f\ud83c\udf2b\ufe0f\ud83c\udf2b\ufe0f\ud83c\udf2b\ufe0f\ud83c\udf2b\ufe0f\ud83c\udf2b\ufe0f\ud83c\udf2b\ufe0f\ud83c\udf2b\ufe0f\ud83c\udf2b\ufe0f\ud83c\udf2b\ufe0f\ud83c\udf2b\ufe0f\ud83c\udf2b\ufe0f\ud83c\udf2b\ufe0f\ud83c\udf2b\ufe0f\ud83c\udf2b\ufe0f\ud83c\udf2b\ufe0f\ud83c\udf2b\ufe0f\ud83c\udf2b\ufe0f\ud83c\udf2b\ufe0f\ud83c\udf2b\ufe0f\ud83c\udf2b\ufe0f\ud83c\udf2b\ufe0f\ud83c\udf2b\ufe0f\ud83c\udf2b\ufe0f\ud83c\udf2b\ufe0f\ud83c\udf2b\ufe0f\ud83c\udf2b\ufe0f\ud83c\udf2b\ufe0f\ud83c\udf2b\ufe0f\ud83c\udf2b\ufe0f\ud83c\udf2b\ufe0f\ud83c\udf2b\ufe0f\ud83c\udf2b\ufe0f\ud83c\udf2b\ufe0f\ud83c\udf2b\ufe0f\ud83c\udf2b\ufe0f\ud83c\udf2b\ufe0f\ud83c\udf2b\ufe0f\ud83c\udf2b\ufe0f\ud83c\udf2b\ufe0f\ud83c\udf2b\ufe0f\ud83c\udf2b\ufe0f\ud83c\udf2b\ufe0f\ud83c\udf2b\ufe0f\ud83c\udf2b\ufe0f\ud83c\udf2b\ufe0f\ud83c\udf2b\ufe0f\ud83c\udf2b\ufe0f\ud83c\udf2b\ufe0f\ud83c\udf2b\ufe0f\ud83c\udf2b\ufe0f\ud83c\udf2b\ufe0f\ud83c\udf2b\ufe0f\ud83c\udf2b\ufe0f\ud83c\udf2b\ufe0f\ud83c\udf2b\ufe0f\ud83c\udf2b\ufe0f\ud83c\udf2b\ufe0f\ud83c\udf2b\ufe0f\ud83c\udf2b\ufe0f\ud83c\udf2b\ufe0f\ud83c\udf2b\ufe0f\ud83c\udf2b\ufe0f\ud83c\udf2b\ufe0f\ud83c\udf2b\ufe0f\ud83c\udf2b\ufe0f\ud83c\udf2b\ufe0f\ud83c\udf2b\ufe0f\ud83c\udf2b\ufe0f\ud83c\udf2b\ufe0f\ud83c\udf2b\ufe0f\ud83c\udf2b\ufe0f\ud83c\udf2b\ufe0f\ud83c\udf2b\ufe0f\ud83c\udf2b\ufe0f\ud83c\udf2b\ufe0f\ud83c\udf2b\ufe0f\ud83c\udf2b\ufe0f\ud83c\udf2b\ufe0f\ud83c\udf2b\ufe0f\ud83c\udf2b\ufe0f\ud83c\udf2b\ufe0f\ud83c\udf2b\ufe0f\ud83c\udf2b\ufe0f\ud83c\udf2b\ufe0f\ud83c\udf2b\ufe0f\ud83c\udf2b\ufe0f\ud83c\udf2b\ufe0f\ud83c\udf2b\ufe0f\ud83c\udf2b\ufe0f\ud83c\udf2b\ufe0f\ud83c\udf2b\ufe0f\ud83c\udf2b\ufe0f\ud83c\udf2b\ufe0f\ud83c\udf2b\ufe0f\ud83c\udf2b\ufe0f\ud83c\udf2b\ufe0f\ud83c\udf2b\ufe0f\ud83c\udf2b\ufe0f\ud83c\udf2b\ufe0f\ud83c\udf2b\ufe0f\ud83c\udf2b\ufe0f\ud83c\udf2b\ufe0f\ud83c\udf2b\ufe0f\ud83c\udf2b\ufe0f\ud83c\udf2b\ufe0f\ud83c\udf2b\ufe0f\ud83c\udf2b\ufe0f\ud83c\udf2b\ufe0f\ud83c\udf2b\ufe0f\ud83c\udf2b\ufe0f\ud83c\udf2b\ufe0f\ud83c\udf2b\ufe0f\ud83c\udf2b\ufe0f\ud83c\udf2b\ufe0f\ud83c\udf2b\ufe0f\ud83c\udf2b\ufe0f\ud83c\udf2b\ufe0f\ud83c\udf2b\ufe0f\ud83c\udf2b\ufe0f"
      }
    },
    {
      "post": {
        "uri": "at://did:plc:mi7pxcpcmcxkgxfedkst7nb2/app.bsky.feed.post/3m32g6iefzc2k",
        "cid": "bafyreid7hplxsllrq3doqkvbtbf2k4jkzizm3eei4by764rr4ppb32tjjq",
        "author": {
          "did": "did:plc:mi7pxcpcmcxkgxfedkst7nb2",
          "handle": "princefarallel.bsky.social",
          "displayName": "Prince Farallel",
          "avatar": "https://cdn.bsky.app/img/avatar/plain/did:plc:mi7pxcpcmcxkgxfedkst7nb2/bafkreibusjosiuxvtueasrfeyiq6usgj7xwqxydavfcikbc7mkrsrrrnki@jpeg",
          "associated": {
            "activitySubscription": {
              "allowSubscriptions": "followers"
            }
          },
          "viewer": {
            "muted": false,
            "blockedBy": false
          },
          "labels": [],
          "createdAt": "2025-05-18T21:42:03.639Z"
        },
        "record": {
          "$type": "app.bsky.feed.post",
          "createdAt": "2025-10-13T04:52:30.208Z",
          "langs": [
            "en"
          ],
          "text": "Oh Diary, what a momentous day!!! Though the prickly political aide (Julia?) was *not* up to task in assembling the components for the blessing, we \u201cmade clamberries into paste\u201d as the commoners say!!!"
        },
        "bookmarkCount": 0,
        "replyCount": 1,
        "repostCount": 0,
        "likeCount": 2,
        "quoteCount": 0,
        "indexedAt": "2025-10-13T04:52:31.083Z",
        "viewer": {
          "bookmarked": false,
          "threadMuted": false,
          "embeddingDisabled": false
        },
        "labels": [],
        "text": "Oh Diary, what a momentous day!!! Though the prickly political aide (Julia?) was *not* up to task in assembling the components for the blessing, we \u201cmade clamberries into paste\u201d as the commoners say!!!"
      }
    }
  ],
  "replies": {
    "at://did:plc:mi7pxcpcmcxkgxfedkst7nb2/app.bsky.feed.post/3m32gb7xgck2k": [
      {
        "post": {
          "uri": "at://did:plc:mi7pxcpcmcxkgxfedkst7nb2/app.bsky.feed.post/3m32h7wcswc2k",
          "cid": "bafyreihpaufbuh72amxo6bvk3qfmxnjchfdb7bosm7xjimsex2w4fmsydu",
          "author": {
            "did": "did:plc:mi7pxcpcmcxkgxfedkst7nb2",
            "handle": "princefarallel.bsky.social",
            "displayName": "Prince Farallel",
            "avatar": "https://cdn.bsky.app/img/avatar/plain/did:plc:mi7pxcpcmcxkgxfedkst7nb2/bafkreibusjosiuxvtueasrfeyiq6usgj7xwqxydavfcikbc7mkrsrrrnki@jpeg",
            "associated": {
              "activitySubscription": {
                "allowSubscriptions": "followers"
              }
            },
            "viewer": {
              "muted": false,
              "blockedBy": false
            },
            "labels": [],
            "createdAt": "2025-05-18T21:42:03.639Z"
          },
          "record": {
            "$type": "app.bsky.feed.post",
            "createdAt": "2025-10-13T05:11:12.132Z",
            "langs": [
              "en"
            ],
            "reply": {
              "parent": {
                "cid": "bafyreie5jdjdakaxoivzpgjo3xrii6rbdwhh6mwwbviwf7yozvh3mtk6ue",
                "uri": "at://did:plc:mi7pxcpcmcxkgxfedkst7nb2/app.bsky.feed.post/3m32gb7xgck2k"
              },
              "root": {
                "cid": "bafyreid7hplxsllrq3doqkvbtbf2k4jkzizm3eei4by764rr4ppb32tjjq",
                "uri": "at://did:plc:mi7pxcpcmcxkgxfedkst7nb2/app.bsky.feed.post/3m32g6iefzc2k"
              }
            },
            "text": "It was through the flames on the bridge that I saw her, Diary \u2013 the fire dancing in her eyes, illuminating their bewitching hue. Her precious mouth agape at the spectacle before her, or perhaps, I must not even wish it\u2026 at the sight of me?"
          },
          "bookmarkCount": 0,
          "replyCount": 0,
          "repostCount": 0,
          "likeCount": 0,
          "quoteCount": 0,
          "indexedAt": "2025-10-13T05:11:12.477Z",
          "viewer": {
            "bookmarked": false,
            "threadMuted": false,
            "embeddingDisabled": false
          },
          "labels": [],
          "text": "It was through the flames on the bridge that I saw her, Diary \u2013 the fire dancing in her eyes, illuminating their bewitching hue. Her precious mouth agape at the spectacle before her, or perhaps, I must not even wish it\u2026 at the sight of me?"
        },
        "reply": {
          "root": {
            "uri": "at://did:plc:mi7pxcpcmcxkgxfedkst7nb2/app.bsky.feed.post/3m32g6iefzc2k",
            "cid": "bafyreid7hplxsllrq3doqkvbtbf2k4jkzizm3eei4by764rr4ppb32tjjq",
            "author": {
              "did": "did:plc:mi7pxcpcmcxkgxfedkst7nb2",
              "handle": "princefarallel.bsky.social",
              "displayName": "Prince Farallel",
              "avatar": "https://cdn.bsky.app/img/avatar/plain/did:plc:mi7pxcpcmcxkgxfedkst7nb2/bafkreibusjosiuxvtueasrfeyiq6usgj7xwqxydavfcikbc7mkrsrrrnki@jpeg",
              "associated": {
                "activitySubscription": {
                  "allowSubscriptions": "followers"
                }
              },
              "viewer": {
                "muted": false,
                "blockedBy": false
              },
              "labels": [],
              "createdAt": "2025-05-18T21:42:03.639Z"
            },
            "record": {
              "$type": "app.bsky.feed.post",
              "createdAt": "2025-10-13T04:52:30.208Z",
              "langs": [
                "en"
              ],
              "text": "Oh Diary, what a momentous day!!! Though the prickly political aide (Julia?) was *not* up to task in assembling the components for the blessing, we \u201cmade clamberries into paste\u201d as the commoners say!!!"
            },
            "bookmarkCount": 0,
            "replyCount": 1,
            "repostCount": 0,
            "likeCount": 2,
            "quoteCount": 0,
            "indexedAt": "2025-10-13T04:52:31.083Z",
            "viewer": {
              "bookmarked": false,
              "threadMuted": false,
              "embeddingDisabled": false
            },
            "labels": [],
            "$type": "app.bsky.feed.defs#postView"
          },
          "parent": {
            "uri": "at://did:plc:mi7pxcpcmcxkgxfedkst7nb2/app.bsky.feed.post/3m32gb7xgck2k",
            "cid": "bafyreie5jdjdakaxoivzpgjo3xrii6rbdwhh6mwwbviwf7yozvh3mtk6ue",
            "author": {
              "did": "did:plc:mi7pxcpcmcxkgxfedkst7nb2",
              "handle": "princefarallel.bsky.social",
              "displayName": "Prince Farallel",
              "avatar": "https://cdn.bsky.app/img/avatar/plain/did:plc:mi7pxcpcmcxkgxfedkst7nb2/bafkreibusjosiuxvtueasrfeyiq6usgj7xwqxydavfcikbc7mkrsrrrnki@jpeg",
              "associated": {
                "activitySubscription": {
                  "allowSubscriptions": "followers"
                }
              },
              "viewer": {
                "muted": false,
                "blockedBy": false
              },
              "labels": [],
              "createdAt": "2025-05-18T21:42:03.639Z"
            },
            "record": {
              "$type": "app.bsky.feed.post",
              "createdAt": "2025-10-13T04:54:02.059Z",
              "langs": [
                "en"
              ],
              "reply": {
                "parent": {
                  "cid": "bafyreid7hplxsllrq3doqkvbtbf2k4jkzizm3eei4by764rr4ppb32tjjq",
                  "uri": "at://did:plc:mi7pxcpcmcxkgxfedkst7nb2/app.bsky.feed.post/3m32g6iefzc2k"
                },
                "root": {
                  "cid": "bafyreid7hplxsllrq3doqkvbtbf2k4jkzizm3eei4by764rr4ppb32tjjq",
                  "uri": "at://did:plc:mi7pxcpcmcxkgxfedkst7nb2/app.bsky.feed.post/3m32g6iefzc2k"
                }
              },
              "text": "Allegedly, Dank Forest ale was \u201cthe best they could get,\u201d and their \u201cstar archer\u201d was a teen girl who had only taken three lessons from her uncle! She shot the ceremonial flaming arrow into the side of the Wandybruck Bridge! Another round of repairs is needed, but we did it once, we can do it again!"
            },
            "bookmarkCount": 0,
            "replyCount": 1,
            "repostCount": 0,
            "likeCount": 0,
            "quoteCount": 0,
            "indexedAt": "2025-10-13T04:54:02.980Z",
            "viewer": {
              "bookmarked": false,
              "threadMuted": false,
              "embeddingDisabled": false
            },
            "labels": [],
            "$type": "app.bsky.feed.defs#postView"
          },
          "grandparentAuthor": {
            "did": "did:plc:mi7pxcpcmcxkgxfedkst7nb2",
            "handle": "princefarallel.bsky.social",
            "displayName": "Prince Farallel",
            "avatar": "https://cdn.bsky.app/img/avatar/plain/did:plc:mi7pxcpcmcxkgxfedkst7nb2/bafkreibusjosiuxvtueasrfeyiq6usgj7xwqxydavfcikbc7mkrsrrrnki@jpeg",
            "associated": {
              "activitySubscription": {
                "allowSubscriptions": "followers"
              }
            },
            "viewer": {
              "muted": false,
              "blockedBy": false
            },
            "labels": [],
            "createdAt": "2025-05-18T21:42:03.639Z"
          }
        }
      }
    ],
    "at://did:plc:mi7pxcpcmcxkgxfedkst7nb2/app.bsky.feed.post/3m32g6iefzc2k": [
      {
        "post": {
          "uri": "at://did:plc:mi7pxcpcmcxkgxfedkst7nb2/app.bsky.feed.post/3m32gb7xgck2k",
          "cid": "bafyreie5jdjdakaxoivzpgjo3xrii6rbdwhh6mwwbviwf7yozvh3mtk6ue",
          "author": {
            "did": "did:plc:mi7pxcpcmcxkgxfedkst7nb2",
            "handle": "princefarallel.bsky.social",
            "displayName": "Prince Farallel",
            "avatar": "https://cdn.bsky.app/img/avatar/plain/did:plc:mi7pxcpcmcxkgxfedkst7nb2/bafkreibusjosiuxvtueasrfeyiq6usgj7xwqxydavfcikbc7mkrsrrrnki@jpeg",
            "associated": {
              "activitySubscription": {
                "allowSubscriptions": "followers"
              }
            },
            "viewer": {
              "muted": false,
              "blockedBy": false
            },
            "labels": [],
            "createdAt": "2025-05-18T21:42:03.639Z"
          },
          "record": {
            "$type": "app.bsky.feed.post",
            "createdAt": "2025-10-13T04:54:02.059Z",
            "langs": [
              "en"
            ],
            "reply": {
              "parent": {
                "cid": "bafyreid7hplxsllrq3doqkvbtbf2k4jkzizm3eei4by764rr4ppb32tjjq",
                "uri": "at://did:plc:mi7pxcpcmcxkgxfedkst7nb2/app.bsky.feed.post/3m32g6iefzc2k"
              },
              "root": {
                "cid": "bafyreid7hplxsllrq3doqkvbtbf2k4jkzizm3eei4by764rr4ppb32tjjq",
                "uri": "at://did:plc:mi7pxcpcmcxkgxfedkst7nb2/app.bsky.feed.post/3m32g6iefzc2k"
              }
            },
            "text": "Allegedly, Dank Forest ale was \u201cthe best they could get,\u201d and their \u201cstar archer\u201d was a teen girl who had only taken three lessons from her uncle! She shot the ceremonial flaming arrow into the side of the Wandybruck Bridge! Another round of repairs is needed, but we did it once, we can do it again!"
          },
          "bookmarkCount": 0,
          "replyCount": 1,
          "repostCount": 0,
          "likeCount": 0,
          "quoteCount": 0,
          "indexedAt": "2025-10-13T04:54:02.980Z",
          "viewer": {
            "bookmarked": false,
            "threadMuted": false,
            "embeddingDisabled": false
          },
          "labels": [],
          "text": "Allegedly, Dank Forest ale was \u201cthe best they could get,\u201d and their \u201cstar archer\u201d was a teen girl who had only taken three lessons from her uncle! She shot the ceremonial flaming arrow into the side of the Wandybruck Bridge! Another round of repairs is needed, but we did it once, we can do it again!"
        },
        "reply": {
          "root": {
            "uri": "at://did:plc:mi7pxcpcmcxkgxfedkst7nb2/app.bsky.feed.post/3m32g6iefzc2k",
            "cid": "bafyreid7hplxsllrq3doqkvbtbf2k4jkzizm3eei4by764rr4ppb32tjjq",
            "author": {
              "did": "did:plc:mi7pxcpcmcxkgxfedkst7nb2",
              "handle": "princefarallel.bsky.social",
              "displayName": "Prince Farallel",
              "avatar": "https://cdn.bsky.app/img/avatar/plain/did:plc:mi7pxcpcmcxkgxfedkst7nb2/bafkreibusjosiuxvtueasrfeyiq6usgj7xwqxydavfcikbc7mkrsrrrnki@jpeg",
              "associated": {
                "activitySubscription": {
                  "allowSubscriptions": "followers"
                }
              },
              "viewer": {
                "muted": false,
                "blockedBy": false
              },
              "labels": [],
              "createdAt": "2025-05-18T21:42:03.639Z"
            },
            "record": {
              "$type": "app.bsky.feed.post",
              "createdAt": "2025-10-13T04:52:30.208Z",
              "langs": [
                "en"
              ],
              "text": "Oh Diary, what a momentous day!!! Though the prickly political aide (Julia?) was *not* up to task in assembling the components for the blessing, we \u201cmade clamberries into paste\u201d as the commoners say!!!"
            },
            "bookmarkCount": 0,
            "replyCount": 1,
            "repostCount": 0,
            "likeCount": 2,
            "quoteCount": 0,
            "indexedAt": "2025-10-13T04:52:31.083Z",
            "viewer": {
              "bookmarked": false,
              "threadMuted": false,
              "embeddingDisabled": false
            },
            "labels": [],
            "$type": "app.bsky.feed.defs#postView"
          },
          "parent": {
            "uri": "at://did:plc:mi7pxcpcmcxkgxfedkst7nb2/app.bsky.feed.post/3m32g6iefzc2k",
            "cid": "bafyreid7hplxsllrq3doqkvbtbf2k4jkzizm3eei4by764rr4ppb32tjjq",
            "author": {
              "did": "did:plc:mi7pxcpcmcxkgxfedkst7nb2",
              "handle": "princefarallel.bsky.social",
              "displayName": "Prince Farallel",
              "avatar": "https://cdn.bsky.app/img/avatar/plain/did:plc:mi7pxcpcmcxkgxfedkst7nb2/bafkreibusjosiuxvtueasrfeyiq6usgj7xwqxydavfcikbc7mkrsrrrnki@jpeg",
              "associated": {
                "activitySubscription": {
                  "allowSubscriptions": "followers"
                }
              },
              "viewer": {
                "muted": false,
                "blockedBy": false
              },
              "labels": [],
              "createdAt": "2025-05-18T21:42:03.639Z"
            },
            "record": {
              "$type": "app.bsky.feed.post",
              "createdAt": "2025-10-13T04:52:30.208Z",
              "langs": [
                "en"
              ],
              "text": "Oh Diary, what a momentous day!!! Though the prickly political aide (Julia?) was *not* up to task in assembling the components for the blessing, we \u201cmade clamberries into paste\u201d as the commoners say!!!"
            },
            "bookmarkCount": 0,
            "replyCount": 1,
            "repostCount": 0,
            "likeCount": 2,
            "quoteCount": 0,
            "indexedAt": "2025-10-13T04:52:31.083Z",
            "viewer": {
              "bookmarked": false,
              "threadMuted": false,
              "embeddingDisabled": false
            },
            "labels": [],
            "$type": "app.bsky.feed.defs#postView"
          }
        }
      }
    ]
  }
}