{
  "mainPosts": [
    {
      "post": {
        "uri": "at://did:plc:4bftfm3fheoh7rw3qinaivem/app.bsky.feed.post/3lls6gvvutk23",
        "cid": "bafyreibmqpmtahynymcv4ap5vd6myis4tujfpe4jmepoq5ngxhk5svfymy",
        "author": {
          "did": "did:plc:4bftfm3fheoh7rw3qinaivem",
          "handle": "rootabegga.bsky.social",
          "displayName": "Rootabegga",
          "avatar": "https://cdn.bsky.app/img/avatar/plain/did:plc:4bftfm3fheoh7rw3qinaivem/bafkreiebwtnfxqxhy6nx2s5yj4hlw3joz56bocbmmad3wukpodijyy2p2y@jpeg",
          "viewer": {
            "muted": false,
            "blockedBy": false,
            "following": "at://did:plc:tsrqneix4sgsbvrhz6arbuci/app.bsky.graph.follow/3lcvq27et5q2d",
            "followedBy": "at://did:plc:4bftfm3fheoh7rw3qinaivem/app.bsky.graph.follow/3lcu4cihm262y"
          },
          "labels": [],
          "createdAt": "2024-12-08T02:09:07.145Z"
        },
        "record": {
          "$type": "app.bsky.feed.post",
          "createdAt": "2025-04-02T00:54:50.591Z",
          "langs": [
            "en"
          ],
          "text": "Met up with Paul and went for another beautiful swim! \ud83d\ude0d\ud83e\udef6\ud83c\udfca\n\nPaul really confided in me today. He's just so special and has such a unique perspective on life. \n\nI think we're going to be friends for a long long time \ud83e\uddd1\u200d\ud83e\udd1d\u200d\ud83e\uddd1\ud83c\udf08\ud83d\udc97\ud83d\udc69\u200d\u2764\ufe0f\u200d\ud83d\udc8b\u200d\ud83d\udc68"
        },
        "replyCount": 0,
        "repostCount": 0,
        "likeCount": 0,
        "quoteCount": 0,
        "indexedAt": "2025-04-02T00:54:50.904Z",
        "viewer": {
          "threadMuted": false,
          "embeddingDisabled": false
        },
        "labels": [],
        "text": "Met up with Paul and went for another beautiful swim! \ud83d\ude0d\ud83e\udef6\ud83c\udfca\n\nPaul really confided in me today. He's just so special and has such a unique perspective on life. \n\nI think we're going to be friends for a long long time \ud83e\uddd1\u200d\ud83e\udd1d\u200d\ud83e\uddd1\ud83c\udf08\ud83d\udc97\ud83d\udc69\u200d\u2764\ufe0f\u200d\ud83d\udc8b\u200d\ud83d\udc68"
      }
    },
    {
      "post": {
        "uri": "at://did:plc:dyhferaekcfoi2ralb473wbi/app.bsky.feed.post/3llscqossmc2c",
        "cid": "bafyreidowk4loy5wetqiprrpuysxldpp33l3t4mrb4voedwgpgxtpoc4yu",
        "author": {
          "did": "did:plc:dyhferaekcfoi2ralb473wbi",
          "handle": "thegreenwizard.bsky.social",
          "displayName": "The Green Wizard",
          "avatar": "https://cdn.bsky.app/img/avatar/plain/did:plc:dyhferaekcfoi2ralb473wbi/bafkreiai2vwa4jpqwzqbbhh4u6mqr6kcombzrhfiyjjxqynjopuyj64yse@jpeg",
          "associated": {
            "chat": {
              "allowIncoming": "following"
            }
          },
          "viewer": {
            "muted": false,
            "blockedBy": false,
            "following": "at://did:plc:tsrqneix4sgsbvrhz6arbuci/app.bsky.graph.follow/3lbsctusxga2q"
          },
          "labels": [],
          "createdAt": "2023-09-20T21:06:29.785Z"
        },
        "record": {
          "$type": "app.bsky.feed.post",
          "createdAt": "2025-04-02T02:11:53.661Z",
          "langs": [
            "en"
          ],
          "text": "Here's a fun riddle I came across the other day:\n\n\"I am a needle in a dragon's cave, where would I be?\"\n\nSound off in the replies! \ud83d\ude0a"
        },
        "replyCount": 0,
        "repostCount": 0,
        "likeCount": 0,
        "quoteCount": 0,
        "indexedAt": "2025-04-02T02:11:54.214Z",
        "viewer": {
          "threadMuted": false,
          "embeddingDisabled": false
        },
        "labels": [],
        "text": "Here's a fun riddle I came across the other day:\n\n\"I am a needle in a dragon's cave, where would I be?\"\n\nSound off in the replies! \ud83d\ude0a"
      }
    }
  ],
  "replies": {}
}