{
  "mainPosts": [
    {
      "post": {
        "uri": "at://did:plc:xe6b2o764pvvqirdprgft3wz/app.bsky.feed.post/3m2uxcbiq7c2y",
        "cid": "bafyreigtsdsmclbthkxrlvghdkspbteomanoh6r7wekwishor4cbtawfwy",
        "author": {
          "did": "did:plc:xe6b2o764pvvqirdprgft3wz",
          "handle": "borrnt.bsky.social",
          "displayName": "Bornt",
          "avatar": "https://cdn.bsky.app/img/avatar/plain/did:plc:xe6b2o764pvvqirdprgft3wz/bafkreiezoub5asat62htzrwlbjtuhxo2nnrq4keilnlkfgqvg7u52nbklq@jpeg",
          "associated": {
            "activitySubscription": {
              "allowSubscriptions": "followers"
            }
          },
          "viewer": {
            "muted": false,
            "blockedBy": false,
            "followedBy": "at://did:plc:xe6b2o764pvvqirdprgft3wz/app.bsky.graph.follow/3lmakf25won2d"
          },
          "labels": [],
          "createdAt": "2025-04-07T17:59:42.893Z"
        },
        "record": {
          "$type": "app.bsky.feed.post",
          "createdAt": "2025-10-11T00:42:52.409Z",
          "facets": [
            {
              "$type": "app.bsky.richtext.facet",
              "features": [
                {
                  "$type": "app.bsky.richtext.facet#mention",
                  "did": "did:plc:qkrs2ei3ebsbwoq6lszwtf53"
                }
              ],
              "index": {
                "byteEnd": 26,
                "byteStart": 8
              }
            }
          ],
          "langs": [
            "en"
          ],
          "text": "TGIF eh @barnt.bsky.social??\n\nThanks Galt, it's Frundee!"
        },
        "bookmarkCount": 0,
        "replyCount": 0,
        "repostCount": 0,
        "likeCount": 0,
        "quoteCount": 0,
        "indexedAt": "2025-10-11T00:42:53.179Z",
        "viewer": {
          "bookmarked": false,
          "threadMuted": false,
          "embeddingDisabled": false
        },
        "labels": [],
        "text": "TGIF eh @barnt.bsky.social??\n\nThanks Galt, it's Frundee!"
      }
    }
  ],
  "replies": {}
}